latinUzConverter/__init__.py
latinUzConverter/core.py
latinUzConverter/letters.py
latinuzconverter-1.0.2.dist-info/LICENSE.txt
latinuzconverter-1.0.2.dist-info/METADATA
latinuzconverter-1.0.2.dist-info/WHEEL
latinuzconverter-1.0.2.dist-info/top_level.txt
latinuzconverter-1.0.2.dist-info/RECORD
