Metadata-Version: 2.1
Name: latinuzconverter
Version: 1.0.2
Summary: A simple package to convert latin text to cyrillic and vice versa.
Home-page: https://github.com/firdavsdev//UzLatinConverterPyPI
Author: DavronbekDev
Author-email: xackercoder@gmail.com
License: UNKNOWN
Platform: UNKNOWN
Classifier: Programming Language :: Python :: 3
Classifier: License :: OSI Approved :: MIT License
Classifier: Operating System :: OS Independent
Requires-Python: >=3.6
License-File: LICENSE.txt
